tstrends/__init__.py
tstrends/label_tuning/__init__.py
tstrends/label_tuning/base.py
tstrends/label_tuning/remaining_value_tuner.py
tstrends/label_tuning/smoothing.py
tstrends/label_tuning/smoothing_direction.py
tstrends/optimization/__init__.py
tstrends/optimization/optimization_bounds.py
tstrends/optimization/optimizer.py
tstrends/py.typed
tstrends/returns_estimation/__init__.py
tstrends/returns_estimation/fees_config.py
tstrends/returns_estimation/returns_estimation.py
tstrends/trend_labelling/__init__.py
tstrends/trend_labelling/base_labeller.py
tstrends/trend_labelling/binary_CTL.py
tstrends/trend_labelling/label_scaling.py
tstrends/trend_labelling/oracle_labeller.py
tstrends/trend_labelling/ternary_CTL.py
tstrends/visualization/__init__.py
tstrends/visualization/utils.py
tstrends-0.4.1.dist-info/METADATA
tstrends-0.4.1.dist-info/WHEEL
tstrends-0.4.1.dist-info/licenses/LICENSE
tstrends-0.4.1.dist-info/RECORD
