Metadata-Version: 2.4
Name: tstrends
Version: 0.4.1
Summary: Advanced trend labelling for time series
License: BSD-2-Clause
License-File: LICENSE
Keywords: time series,trend detection,trend labelling,downtrend,uptrend,quant,quantitative finance,forecasting,financial tools,machine learning
Author: Abel G Penas
Author-email: agpenas.dev@gmail.com
Maintainer: Abel G Penas
Maintainer-email: agpenas.dev@gmail.com
Requires-Python: >=3.10
Classifier: Intended Audience :: Developers
Classifier: Intended Audience :: Financial and Insurance Industry
Classifier: Intended Audience :: Science/Research
Classifier: License :: OSI Approved :: BSD License
Classifier: Operating System :: OS Independent
Classifier: Programming Language :: Python :: 3
Classifier: Programming Language :: Python :: 3.10
Classifier: Programming Language :: Python :: 3.11
Classifier: Programming Language :: Python :: 3.12
Classifier: Programming Language :: Python :: 3.13
Classifier: Programming Language :: Python :: 3.14
Requires-Dist: bayesian-optimization (>=2.0.3,<3.0.0)
Requires-Dist: matplotlib (>=3.10.0,<4.0.0) ; python_version == "3.10"
Requires-Dist: matplotlib (>=3.10.7,<4.0.0) ; python_version >= "3.14"
Requires-Dist: numpy (>=2.2.3,<3.0.0)
Requires-Dist: pandas (>=2.2.3,<3.0.0)
Requires-Dist: pillow (>=11.1.0,<12.0.0) ; python_version == "3.10"
Requires-Dist: pillow (>=12.0.0,<13.0.0) ; python_version >= "3.14"
Requires-Dist: scipy (>=1.15.0,<2.0.0) ; python_version == "3.10"
Requires-Dist: scipy (>=1.16.0,<2.0.0) ; python_version >= "3.11"
Project-URL: Documentation, https://tstrends.xyz
Project-URL: Repository, https://github.com/agpenas/tstrends
